gendock/__init__.py
gendock/gendock.py
gendock/scripts/__init__.py
gendock/scripts/docking.py
gendock/scripts/functional_groups.py
gendock/scripts/learn.py
gendock/scripts/molgen.py
gendock-1.0.dist-info/LICENSE.txt
gendock-1.0.dist-info/METADATA
gendock-1.0.dist-info/WHEEL
gendock-1.0.dist-info/top_level.txt
gendock-1.0.dist-info/RECORD
