Metadata-Version: 2.1
Name: gendock
Version: 1.0
Summary: Python package for generating and docking molecules against macromolecules
Home-page: https://github.com/philspence/gendock
Author: Phil Spence
Author-email: philspence91@gmail.com
License: UNKNOWN
Platform: UNKNOWN
Classifier: Programming Language :: Python :: 3
Classifier: Operating System :: MacOS
Classifier: Operating System :: POSIX :: Linux
Classifier: Development Status :: 3 - Alpha
Requires-Python: >=3.6
